{
    "descriptors" : [], 
    "FIPS" : "20003", 
    "full_name" : "Anderson County", 
    "common_name" : "", 
    "state" : "Kansas", 
    "county_seat" : "Garnett", 
    "population" : 8046, 
    "population_desity" : 13.8, 
    "pop_change_rate" : -5.6, 
    "land_area" : 583.73, 
    "white_population" : 7843, 
    "black_population" : 40, 
    "native_indian_population" : 39, 
    "asian_population" : 37, 
    "pacific_islander_population" : 1, 
    "hispanic_population" : 123, 
    "other_race_ethnicity_population" : 42, 
    "multiple_race_population" : 100, 
    "pop_male" : 4013, 
    "pop_female" : 4089, 
    "pop_0to4" : 563, 
    "pop_5to9" : 597, 
    "pop_10to14" : 561, 
    "pop_15to19" : 522, 
    "pop_20to24" : 353, 
    "pop_25to34" : 821, 
    "pop_35to44" : 918, 
    "pop_45to54" : 1148, 
    "pop_55to64" : 986, 
    "pop_65to74" : 830, 
    "pop_75to84" : 515, 
    "pop_85to120" : 288, 
    "median_age" : 42.0, 
    "median_age_male" : 40.7, 
    "median_age_female" : 43.2, 
    "number_households" : 3260, 
    "average_household_size" : 2.45, 
    "number_households_singleM_wo_child" : 407, 
    "number_households_singleF_wo_child" : 512, 
    "number_households_married_w_child" : 714, 
    "number_households_married_wo_child" : 1090, 
    "number_households_singleM_w_child" : 102, 
    "number_households_singleF_w_child" : 183, 
    "number_families" : 2213, 
    "average_family_size" : 3.0, 
    "housing_units" : 3260, 
    "housing_vacant" : 460, 
    "owner_occupied_housing" : 2509, 
    "renter_occupied_housing" : 751, 
    "number_farms" : 707, 
    "average_farm_acreage" : 518, 
    "total_crop_acreage" : 223964
}