{
    "descriptors" : [], 
    "FIPS" : "24045", 
    "full_name" : "Wicomico County", 
    "common_name" : "", 
    "state" : "Maryland", 
    "county_seat" : "Salisbury", 
    "population" : 104808, 
    "population_desity" : 275.8, 
    "pop_change_rate" : 607.5, 
    "land_area" : 379.95, 
    "white_population" : 67784, 
    "black_population" : 23873, 
    "native_indian_population" : 236, 
    "asian_population" : 2471, 
    "pacific_islander_population" : 47, 
    "hispanic_population" : 4478, 
    "other_race_ethnicity_population" : 1872, 
    "multiple_race_population" : 2450, 
    "pop_male" : 47087, 
    "pop_female" : 51646, 
    "pop_0to4" : 6142, 
    "pop_5to9" : 6140, 
    "pop_10to14" : 6009, 
    "pop_15to19" : 8968, 
    "pop_20to24" : 9337, 
    "pop_25to34" : 12044, 
    "pop_35to44" : 11610, 
    "pop_45to54" : 14013, 
    "pop_55to64" : 11623, 
    "pop_65to74" : 6866, 
    "pop_75to84" : 4210, 
    "pop_85to120" : 1771, 
    "median_age" : 35.7, 
    "median_age_male" : 34.4, 
    "median_age_female" : 36.8, 
    "number_households" : 37220, 
    "average_household_size" : 2.53, 
    "number_households_singleM_wo_child" : 3792, 
    "number_households_singleF_wo_child" : 5613, 
    "number_households_married_w_child" : 6856, 
    "number_households_married_wo_child" : 9842, 
    "number_households_singleM_w_child" : 1068, 
    "number_households_singleF_w_child" : 3909, 
    "number_families" : 24172, 
    "average_family_size" : 3.01, 
    "housing_units" : 37220, 
    "housing_vacant" : 3972, 
    "owner_occupied_housing" : 23317, 
    "renter_occupied_housing" : 13903, 
    "number_farms" : 510, 
    "average_farm_acreage" : 164, 
    "total_crop_acreage" : 56094
}