{
    "descriptors" : [], 
    "FIPS" : "42051", 
    "full_name" : "Fayette County", 
    "common_name" : "", 
    "state" : "Pennsylvania", 
    "county_seat" : "Uniontown", 
    "population" : 131508, 
    "population_desity" : 164.6, 
    "pop_change_rate" : -509.8, 
    "land_area" : 798.73, 
    "white_population" : 127418, 
    "black_population" : 6325, 
    "native_indian_population" : 184, 
    "asian_population" : 405, 
    "pacific_islander_population" : 24, 
    "hispanic_population" : 1049, 
    "other_race_ethnicity_population" : 411, 
    "multiple_race_population" : 1839, 
    "pop_male" : 67007, 
    "pop_female" : 69599, 
    "pop_0to4" : 6810, 
    "pop_5to9" : 7430, 
    "pop_10to14" : 8136, 
    "pop_15to19" : 8382, 
    "pop_20to24" : 7357, 
    "pop_25to34" : 15016, 
    "pop_35to44" : 17799, 
    "pop_45to54" : 21270, 
    "pop_55to64" : 19826, 
    "pop_65to74" : 12200, 
    "pop_75to84" : 8518, 
    "pop_85to120" : 3862, 
    "median_age" : 43.6, 
    "median_age_male" : 42.0, 
    "median_age_female" : 45.2, 
    "number_households" : 55997, 
    "average_household_size" : 2.36, 
    "number_households_singleM_wo_child" : 6952, 
    "number_households_singleF_wo_child" : 9326, 
    "number_households_married_w_child" : 9368, 
    "number_households_married_wo_child" : 17498, 
    "number_households_singleM_w_child" : 1522, 
    "number_households_singleF_w_child" : 4403, 
    "number_families" : 37068, 
    "average_family_size" : 2.89, 
    "housing_units" : 55997, 
    "housing_vacant" : 6776, 
    "owner_occupied_housing" : 40247, 
    "renter_occupied_housing" : 15750, 
    "number_farms" : 941, 
    "average_farm_acreage" : 120, 
    "total_crop_acreage" : 55185
}