{
    "descriptors" : [], 
    "FIPS" : "42111", 
    "full_name" : "Somerset County", 
    "common_name" : "", 
    "state" : "Pennsylvania", 
    "county_seat" : "Somerset", 
    "population" : 75239, 
    "population_desity" : 69.6, 
    "pop_change_rate" : -250.3, 
    "land_area" : 1081.66, 
    "white_population" : 74603, 
    "black_population" : 1863, 
    "native_indian_population" : 86, 
    "asian_population" : 239, 
    "pacific_islander_population" : 17, 
    "hispanic_population" : 840, 
    "other_race_ethnicity_population" : 468, 
    "multiple_race_population" : 466, 
    "pop_male" : 40029, 
    "pop_female" : 37713, 
    "pop_0to4" : 3702, 
    "pop_5to9" : 4078, 
    "pop_10to14" : 4467, 
    "pop_15to19" : 4548, 
    "pop_20to24" : 4077, 
    "pop_25to34" : 8656, 
    "pop_35to44" : 10147, 
    "pop_45to54" : 12449, 
    "pop_55to64" : 11187, 
    "pop_65to74" : 7115, 
    "pop_75to84" : 4928, 
    "pop_85to120" : 2388, 
    "median_age" : 44.2, 
    "median_age_male" : 42.5, 
    "median_age_female" : 46.1, 
    "number_households" : 31090, 
    "average_household_size" : 2.35, 
    "number_households_singleM_wo_child" : 3888, 
    "number_households_singleF_wo_child" : 4841, 
    "number_households_married_w_child" : 5925, 
    "number_households_married_wo_child" : 11008, 
    "number_households_singleM_w_child" : 745, 
    "number_households_singleF_w_child" : 1502, 
    "number_families" : 21025, 
    "average_family_size" : 2.87, 
    "housing_units" : 31090, 
    "housing_vacant" : 7023, 
    "owner_occupied_housing" : 23885, 
    "renter_occupied_housing" : 7205, 
    "number_farms" : 1140, 
    "average_farm_acreage" : 188, 
    "total_crop_acreage" : 119396
}