{
    "descriptors" : [], 
    "FIPS" : "01075", 
    "full_name" : "Lamar County", 
    "common_name" : "", 
    "state" : "Alabama", 
    "county_seat" : "Vernon", 
    "population" : 14722, 
    "population_desity" : 24.3, 
    "pop_change_rate" : 15.8, 
    "land_area" : 605.47, 
    "white_population" : 12626, 
    "black_population" : 1643, 
    "native_indian_population" : 24, 
    "asian_population" : 4, 
    "pacific_islander_population" : 2, 
    "hispanic_population" : 180, 
    "other_race_ethnicity_population" : 82, 
    "multiple_race_population" : 183, 
    "pop_male" : 7097, 
    "pop_female" : 7467, 
    "pop_0to4" : 861, 
    "pop_5to9" : 892, 
    "pop_10to14" : 933, 
    "pop_15to19" : 865, 
    "pop_20to24" : 731, 
    "pop_25to34" : 1466, 
    "pop_35to44" : 1814, 
    "pop_45to54" : 2210, 
    "pop_55to64" : 2060, 
    "pop_65to74" : 1547, 
    "pop_75to84" : 914, 
    "pop_85to120" : 271, 
    "median_age" : 43.5, 
    "median_age_male" : 42.4, 
    "median_age_female" : 44.5, 
    "number_households" : 6103, 
    "average_household_size" : 2.35, 
    "number_households_singleM_wo_child" : 804, 
    "number_households_singleF_wo_child" : 953, 
    "number_households_married_w_child" : 1203, 
    "number_households_married_wo_child" : 2042, 
    "number_households_singleM_w_child" : 137, 
    "number_households_singleF_w_child" : 452, 
    "number_families" : 4207, 
    "average_family_size" : 2.88, 
    "housing_units" : 6103, 
    "housing_vacant" : 1251, 
    "owner_occupied_housing" : 4469, 
    "renter_occupied_housing" : 1634, 
    "number_farms" : 353, 
    "average_farm_acreage" : 233, 
    "total_crop_acreage" : 13868
}