{
    "descriptors" : [], 
    "FIPS" : "01099", 
    "full_name" : "Monroe County", 
    "common_name" : "", 
    "state" : "Alabama", 
    "county_seat" : "Monroeville", 
    "population" : 22898, 
    "population_desity" : 22.1, 
    "pop_change_rate" : -17.0, 
    "land_area" : 1034.4, 
    "white_population" : 12718, 
    "black_population" : 9614, 
    "native_indian_population" : 260, 
    "asian_population" : 67, 
    "pacific_islander_population" : 9, 
    "hispanic_population" : 220, 
    "other_race_ethnicity_population" : 66, 
    "multiple_race_population" : 334, 
    "pop_male" : 11109, 
    "pop_female" : 11959, 
    "pop_0to4" : 1382, 
    "pop_5to9" : 1532, 
    "pop_10to14" : 1782, 
    "pop_15to19" : 1821, 
    "pop_20to24" : 1172, 
    "pop_25to34" : 2418, 
    "pop_35to44" : 2873, 
    "pop_45to54" : 3391, 
    "pop_55to64" : 3079, 
    "pop_65to74" : 1984, 
    "pop_75to84" : 1186, 
    "pop_85to120" : 448, 
    "median_age" : 40.1, 
    "median_age_male" : 38.2, 
    "median_age_female" : 41.5, 
    "number_households" : 9214, 
    "average_household_size" : 2.48, 
    "number_households_singleM_wo_child" : 1182, 
    "number_households_singleF_wo_child" : 1341, 
    "number_households_married_w_child" : 1805, 
    "number_households_married_wo_child" : 2524, 
    "number_households_singleM_w_child" : 231, 
    "number_households_singleF_w_child" : 1131, 
    "number_families" : 6410, 
    "average_family_size" : 3.01, 
    "housing_units" : 9214, 
    "housing_vacant" : 2119, 
    "owner_occupied_housing" : 7077, 
    "renter_occupied_housing" : 2137, 
    "number_farms" : 480, 
    "average_farm_acreage" : 293, 
    "total_crop_acreage" : 53898
}