{
    "descriptors" : [], 
    "FIPS" : "41055", 
    "full_name" : "Sherman County", 
    "common_name" : "", 
    "state" : "Oregon", 
    "county_seat" : "Moro", 
    "population" : 1776, 
    "population_desity" : 2.1, 
    "pop_change_rate" : 1.1, 
    "land_area" : 831.18, 
    "white_population" : 1648, 
    "black_population" : 4, 
    "native_indian_population" : 29, 
    "asian_population" : 3, 
    "pacific_islander_population" : 1, 
    "hispanic_population" : 98, 
    "other_race_ethnicity_population" : 48, 
    "multiple_race_population" : 32, 
    "pop_male" : 896, 
    "pop_female" : 869, 
    "pop_0to4" : 93, 
    "pop_5to9" : 94, 
    "pop_10to14" : 99, 
    "pop_15to19" : 95, 
    "pop_20to24" : 80, 
    "pop_25to34" : 177, 
    "pop_35to44" : 163, 
    "pop_45to54" : 315, 
    "pop_55to64" : 265, 
    "pop_65to74" : 203, 
    "pop_75to84" : 136, 
    "pop_85to120" : 45, 
    "median_age" : 47.8, 
    "median_age_male" : 47.7, 
    "median_age_female" : 47.9, 
    "number_households" : 777, 
    "average_household_size" : 2.27, 
    "number_households_singleM_wo_child" : 132, 
    "number_households_singleF_wo_child" : 105, 
    "number_households_married_w_child" : 128, 
    "number_households_married_wo_child" : 270, 
    "number_households_singleM_w_child" : 12, 
    "number_households_singleF_w_child" : 34, 
    "number_families" : 492, 
    "average_family_size" : 2.84, 
    "housing_units" : 777, 
    "housing_vacant" : 141, 
    "owner_occupied_housing" : 524, 
    "renter_occupied_housing" : 253, 
    "number_farms" : 186, 
    "average_farm_acreage" : 2762, 
    "total_crop_acreage" : 365078
}