{
    "descriptors" : [], 
    "FIPS" : "45085", 
    "full_name" : "Sumter County", 
    "common_name" : "", 
    "state" : "South Carolina", 
    "county_seat" : "Sumter", 
    "population" : 110435, 
    "population_desity" : 161.9, 
    "pop_change_rate" : 297.9, 
    "land_area" : 682.08, 
    "white_population" : 51825, 
    "black_population" : 50414, 
    "native_indian_population" : 389, 
    "asian_population" : 1188, 
    "pacific_islander_population" : 99, 
    "hispanic_population" : 3532, 
    "other_race_ethnicity_population" : 1511, 
    "multiple_race_population" : 2030, 
    "pop_male" : 51732, 
    "pop_female" : 55724, 
    "pop_0to4" : 7949, 
    "pop_5to9" : 7419, 
    "pop_10to14" : 7503, 
    "pop_15to19" : 7921, 
    "pop_20to24" : 8218, 
    "pop_25to34" : 14198, 
    "pop_35to44" : 12996, 
    "pop_45to54" : 15188, 
    "pop_55to64" : 12143, 
    "pop_65to74" : 7883, 
    "pop_75to84" : 4323, 
    "pop_85to120" : 1715, 
    "median_age" : 35.4, 
    "median_age_male" : 33.4, 
    "median_age_female" : 37.4, 
    "number_households" : 40398, 
    "average_household_size" : 2.59, 
    "number_households_singleM_wo_child" : 4775, 
    "number_households_singleF_wo_child" : 5667, 
    "number_households_married_w_child" : 7932, 
    "number_households_married_wo_child" : 10098, 
    "number_households_singleM_w_child" : 1181, 
    "number_households_singleF_w_child" : 5451, 
    "number_families" : 28311, 
    "average_family_size" : 3.11, 
    "housing_units" : 40398, 
    "housing_vacant" : 5613, 
    "owner_occupied_housing" : 27014, 
    "renter_occupied_housing" : 13384, 
    "number_farms" : 515, 
    "average_farm_acreage" : 342, 
    "total_crop_acreage" : 69467
}