{
    "descriptors" : [], 
    "FIPS" : "17087", 
    "full_name" : "Johnson County", 
    "common_name" : "", 
    "state" : "Illinois", 
    "county_seat" : "Vienna", 
    "population" : 12366, 
    "population_desity" : 35.5, 
    "pop_change_rate" : -21.6, 
    "land_area" : 348.68, 
    "white_population" : 11197, 
    "black_population" : 1006, 
    "native_indian_population" : 29, 
    "asian_population" : 22, 
    "pacific_islander_population" : 1, 
    "hispanic_population" : 376, 
    "other_race_ethnicity_population" : 201, 
    "multiple_race_population" : 126, 
    "pop_male" : 7018, 
    "pop_female" : 5564, 
    "pop_0to4" : 566, 
    "pop_5to9" : 695, 
    "pop_10to14" : 710, 
    "pop_15to19" : 815, 
    "pop_20to24" : 763, 
    "pop_25to34" : 1566, 
    "pop_35to44" : 1668, 
    "pop_45to54" : 1922, 
    "pop_55to64" : 1710, 
    "pop_65to74" : 1295, 
    "pop_75to84" : 653, 
    "pop_85to120" : 219, 
    "median_age" : 42.2, 
    "median_age_male" : 39.8, 
    "median_age_female" : 45.4, 
    "number_households" : 4584, 
    "average_household_size" : 2.41, 
    "number_households_singleM_wo_child" : 544, 
    "number_households_singleF_wo_child" : 616, 
    "number_households_married_w_child" : 943, 
    "number_households_married_wo_child" : 1770, 
    "number_households_singleM_w_child" : 104, 
    "number_households_singleF_w_child" : 249, 
    "number_families" : 3270, 
    "average_family_size" : 2.85, 
    "housing_units" : 4584, 
    "housing_vacant" : 1014, 
    "owner_occupied_housing" : 3756, 
    "renter_occupied_housing" : 828, 
    "number_farms" : 558, 
    "average_farm_acreage" : 161, 
    "total_crop_acreage" : 48244
}