{
    "descriptors" : [], 
    "FIPS" : "04013", 
    "full_name" : "Maricopa County", 
    "common_name" : "", 
    "state" : "Arizona", 
    "county_seat" : "Phoenix", 
    "population" : 4477918, 
    "population_desity" : 485.4, 
    "pop_change_rate" : 66080.1, 
    "land_area" : 9225.99, 
    "white_population" : 2786781, 
    "black_population" : 190519, 
    "native_indian_population" : 78329, 
    "asian_population" : 132225, 
    "pacific_islander_population" : 7790, 
    "hispanic_population" : 1128741, 
    "other_race_ethnicity_population" : 489705, 
    "multiple_race_population" : 131768, 
    "pop_male" : 1888465, 
    "pop_female" : 1928652, 
    "pop_0to4" : 282770, 
    "pop_5to9" : 282709, 
    "pop_10to14" : 277228, 
    "pop_15to19" : 276899, 
    "pop_20to24" : 266872, 
    "pop_25to34" : 541126, 
    "pop_35to44" : 524598, 
    "pop_45to54" : 503965, 
    "pop_55to64" : 398309, 
    "pop_65to74" : 255388, 
    "pop_75to84" : 148199, 
    "pop_85to120" : 59054, 
    "median_age" : 34.6, 
    "median_age_male" : 33.5, 
    "median_age_female" : 35.7, 
    "number_households" : 1411583, 
    "average_household_size" : 2.67, 
    "number_households_singleM_wo_child" : 166796, 
    "number_households_singleF_wo_child" : 198416, 
    "number_households_married_w_child" : 316667, 
    "number_households_married_wo_child" : 358390, 
    "number_households_singleM_w_child" : 51702, 
    "number_households_singleF_w_child" : 119947, 
    "number_families" : 932814, 
    "average_family_size" : 3.25, 
    "housing_units" : 1411583, 
    "housing_vacant" : 227696, 
    "owner_occupied_housing" : 910320, 
    "renter_occupied_housing" : 501263, 
    "number_farms" : 2479, 
    "average_farm_acreage" : 192, 
    "total_crop_acreage" : 222469
}