{
    "descriptors" : [], 
    "FIPS" : "21151", 
    "full_name" : "Madison County", 
    "common_name" : "", 
    "state" : "Kentucky", 
    "county_seat" : "Richmond", 
    "population" : 92811, 
    "population_desity" : 209.4, 
    "pop_change_rate" : 989.5, 
    "land_area" : 443.26, 
    "white_population" : 75926, 
    "black_population" : 3611, 
    "native_indian_population" : 250, 
    "asian_population" : 758, 
    "pacific_islander_population" : 33, 
    "hispanic_population" : 1813, 
    "other_race_ethnicity_population" : 683, 
    "multiple_race_population" : 1655, 
    "pop_male" : 40264, 
    "pop_female" : 42652, 
    "pop_0to4" : 5069, 
    "pop_5to9" : 4990, 
    "pop_10to14" : 4945, 
    "pop_15to19" : 7181, 
    "pop_20to24" : 9492, 
    "pop_25to34" : 11173, 
    "pop_35to44" : 10751, 
    "pop_45to54" : 10888, 
    "pop_55to64" : 9115, 
    "pop_65to74" : 5336, 
    "pop_75to84" : 2897, 
    "pop_85to120" : 1079, 
    "median_age" : 33.7, 
    "median_age_male" : 32.8, 
    "median_age_female" : 34.7, 
    "number_households" : 31973, 
    "average_household_size" : 2.42, 
    "number_households_singleM_wo_child" : 3770, 
    "number_households_singleF_wo_child" : 4653, 
    "number_households_married_w_child" : 6828, 
    "number_households_married_wo_child" : 8915, 
    "number_households_singleM_w_child" : 822, 
    "number_households_singleF_w_child" : 2488, 
    "number_families" : 20899, 
    "average_family_size" : 2.92, 
    "housing_units" : 31973, 
    "housing_vacant" : 3070, 
    "owner_occupied_housing" : 19481, 
    "renter_occupied_housing" : 12492, 
    "number_farms" : 1219, 
    "average_farm_acreage" : 191, 
    "total_crop_acreage" : 72977
}