{
    "descriptors" : [], 
    "FIPS" : "53045", 
    "full_name" : "Mason County", 
    "common_name" : "", 
    "state" : "Washington", 
    "county_seat" : "Shelton", 
    "population" : 65996, 
    "population_desity" : 67.8, 
    "pop_change_rate" : 529.7, 
    "land_area" : 972.73, 
    "white_population" : 52281, 
    "black_population" : 659, 
    "native_indian_population" : 2239, 
    "asian_population" : 731, 
    "pacific_islander_population" : 227, 
    "hispanic_population" : 4844, 
    "other_race_ethnicity_population" : 2049, 
    "multiple_race_population" : 2513, 
    "pop_male" : 31400, 
    "pop_female" : 29299, 
    "pop_0to4" : 3278, 
    "pop_5to9" : 3357, 
    "pop_10to14" : 3513, 
    "pop_15to19" : 3688, 
    "pop_20to24" : 3124, 
    "pop_25to34" : 6903, 
    "pop_35to44" : 6951, 
    "pop_45to54" : 9171, 
    "pop_55to64" : 9602, 
    "pop_65to74" : 6564, 
    "pop_75to84" : 3430, 
    "pop_85to120" : 1118, 
    "median_age" : 44.3, 
    "median_age_male" : 42.7, 
    "median_age_female" : 46.0, 
    "number_households" : 23832, 
    "average_household_size" : 2.45, 
    "number_households_singleM_wo_child" : 3015, 
    "number_households_singleF_wo_child" : 3021, 
    "number_households_married_w_child" : 3961, 
    "number_households_married_wo_child" : 8542, 
    "number_households_singleM_w_child" : 807, 
    "number_households_singleF_w_child" : 1469, 
    "number_families" : 16057, 
    "average_family_size" : 2.87, 
    "housing_units" : 23832, 
    "housing_vacant" : 8686, 
    "owner_occupied_housing" : 18474, 
    "renter_occupied_housing" : 5358, 
    "number_farms" : 377, 
    "average_farm_acreage" : 63, 
    "total_crop_acreage" : 4754
}