{
    "descriptors" : [], 
    "FIPS" : "05137", 
    "full_name" : "Stone County", 
    "common_name" : "", 
    "state" : "Arkansas", 
    "county_seat" : "Mountain View", 
    "population" : 13487, 
    "population_desity" : 22.1, 
    "pop_change_rate" : 109.3, 
    "land_area" : 609.59, 
    "white_population" : 11995, 
    "black_population" : 11, 
    "native_indian_population" : 84, 
    "asian_population" : 45, 
    "pacific_islander_population" : 4, 
    "hispanic_population" : 157, 
    "other_race_ethnicity_population" : 55, 
    "multiple_race_population" : 200, 
    "pop_male" : 6128, 
    "pop_female" : 6266, 
    "pop_0to4" : 692, 
    "pop_5to9" : 697, 
    "pop_10to14" : 738, 
    "pop_15to19" : 684, 
    "pop_20to24" : 508, 
    "pop_25to34" : 1176, 
    "pop_35to44" : 1227, 
    "pop_45to54" : 1893, 
    "pop_55to64" : 1953, 
    "pop_65to74" : 1671, 
    "pop_75to84" : 870, 
    "pop_85to120" : 285, 
    "median_age" : 47.5, 
    "median_age_male" : 46.7, 
    "median_age_female" : 48.3, 
    "number_households" : 5325, 
    "average_household_size" : 2.3, 
    "number_households_singleM_wo_child" : 719, 
    "number_households_singleF_wo_child" : 818, 
    "number_households_married_w_child" : 991, 
    "number_households_married_wo_child" : 1985, 
    "number_households_singleM_w_child" : 138, 
    "number_households_singleF_w_child" : 237, 
    "number_families" : 3590, 
    "average_family_size" : 2.81, 
    "housing_units" : 5325, 
    "housing_vacant" : 1387, 
    "owner_occupied_housing" : 4142, 
    "renter_occupied_housing" : 1183, 
    "number_farms" : 523, 
    "average_farm_acreage" : 259, 
    "total_crop_acreage" : 22062
}