{
    "descriptors" : [], 
    "FIPS" : "30091", 
    "full_name" : "Sheridan County", 
    "common_name" : "", 
    "state" : "Montana", 
    "county_seat" : "Plentywood", 
    "population" : 3402, 
    "population_desity" : 2.0, 
    "pop_change_rate" : 1.8, 
    "land_area" : 1705.97, 
    "white_population" : 3229, 
    "black_population" : 7, 
    "native_indian_population" : 57, 
    "asian_population" : 14, 
    "pacific_islander_population" : 0, 
    "hispanic_population" : 51, 
    "other_race_ethnicity_population" : 11, 
    "multiple_race_population" : 66, 
    "pop_male" : 1698, 
    "pop_female" : 1686, 
    "pop_0to4" : 153, 
    "pop_5to9" : 161, 
    "pop_10to14" : 204, 
    "pop_15to19" : 187, 
    "pop_20to24" : 121, 
    "pop_25to34" : 275, 
    "pop_35to44" : 323, 
    "pop_45to54" : 586, 
    "pop_55to64" : 592, 
    "pop_65to74" : 353, 
    "pop_75to84" : 295, 
    "pop_85to120" : 134, 
    "median_age" : 50.3, 
    "median_age_male" : 49.8, 
    "median_age_female" : 50.8, 
    "number_households" : 1587, 
    "average_household_size" : 2.08, 
    "number_households_singleM_wo_child" : 302, 
    "number_households_singleF_wo_child" : 287, 
    "number_households_married_w_child" : 233, 
    "number_households_married_wo_child" : 552, 
    "number_households_singleM_w_child" : 42, 
    "number_households_singleF_w_child" : 57, 
    "number_families" : 944, 
    "average_family_size" : 2.7, 
    "housing_units" : 1587, 
    "housing_vacant" : 502, 
    "owner_occupied_housing" : 1206, 
    "renter_occupied_housing" : 381, 
    "number_farms" : 527, 
    "average_farm_acreage" : 1977, 
    "total_crop_acreage" : 695965
}