{
    "descriptors" : [], 
    "FIPS" : "38005", 
    "full_name" : "Benson County", 
    "common_name" : "", 
    "state" : "North Dakota", 
    "county_seat" : "Minnewaukan", 
    "population" : 6908, 
    "population_desity" : 4.8, 
    "pop_change_rate" : 24.8, 
    "land_area" : 1439.4, 
    "white_population" : 2889, 
    "black_population" : 1, 
    "native_indian_population" : 3663, 
    "asian_population" : 3, 
    "pacific_islander_population" : 1, 
    "hispanic_population" : 77, 
    "other_race_ethnicity_population" : 10, 
    "multiple_race_population" : 93, 
    "pop_male" : 3379, 
    "pop_female" : 3281, 
    "pop_0to4" : 656, 
    "pop_5to9" : 657, 
    "pop_10to14" : 584, 
    "pop_15to19" : 533, 
    "pop_20to24" : 391, 
    "pop_25to34" : 724, 
    "pop_35to44" : 699, 
    "pop_45to54" : 830, 
    "pop_55to64" : 733, 
    "pop_65to74" : 462, 
    "pop_75to84" : 291, 
    "pop_85to120" : 100, 
    "median_age" : 31.8, 
    "median_age_male" : 31.2, 
    "median_age_female" : 32.4, 
    "number_households" : 2233, 
    "average_household_size" : 2.98, 
    "number_households_singleM_wo_child" : 308, 
    "number_households_singleF_wo_child" : 209, 
    "number_households_married_w_child" : 374, 
    "number_households_married_wo_child" : 570, 
    "number_households_singleM_w_child" : 161, 
    "number_households_singleF_w_child" : 371, 
    "number_families" : 1628, 
    "average_family_size" : 3.46, 
    "housing_units" : 2233, 
    "housing_vacant" : 717, 
    "owner_occupied_housing" : 1517, 
    "renter_occupied_housing" : 716, 
    "number_farms" : 563, 
    "average_farm_acreage" : 1425, 
    "total_crop_acreage" : 644352
}