{
    "descriptors" : [], 
    "FIPS" : "37057", 
    "full_name" : "Davidson County", 
    "common_name" : "", 
    "state" : "North Carolina", 
    "county_seat" : "Lexington", 
    "population" : 173692, 
    "population_desity" : 306.0, 
    "pop_change_rate" : 1081.4, 
    "land_area" : 567.7, 
    "white_population" : 137359, 
    "black_population" : 14421, 
    "native_indian_population" : 794, 
    "asian_population" : 1994, 
    "pacific_islander_population" : 27, 
    "hispanic_population" : 10408, 
    "other_race_ethnicity_population" : 5871, 
    "multiple_race_population" : 2412, 
    "pop_male" : 79797, 
    "pop_female" : 83081, 
    "pop_0to4" : 9975, 
    "pop_5to9" : 10861, 
    "pop_10to14" : 11213, 
    "pop_15to19" : 10656, 
    "pop_20to24" : 8348, 
    "pop_25to34" : 18260, 
    "pop_35to44" : 23791, 
    "pop_45to54" : 25460, 
    "pop_55to64" : 20926, 
    "pop_65to74" : 13583, 
    "pop_75to84" : 7350, 
    "pop_85to120" : 2455, 
    "median_age" : 40.3, 
    "median_age_male" : 39.3, 
    "median_age_female" : 41.2, 
    "number_households" : 64515, 
    "average_household_size" : 2.5, 
    "number_households_singleM_wo_child" : 6961, 
    "number_households_singleF_wo_child" : 8691, 
    "number_households_married_w_child" : 14209, 
    "number_households_married_wo_child" : 20350, 
    "number_households_singleM_w_child" : 2032, 
    "number_households_singleF_w_child" : 5246, 
    "number_families" : 45972, 
    "average_family_size" : 2.94, 
    "housing_units" : 64515, 
    "housing_vacant" : 8140, 
    "owner_occupied_housing" : 46832, 
    "renter_occupied_housing" : 17683, 
    "number_farms" : 1062, 
    "average_farm_acreage" : 82, 
    "total_crop_acreage" : 40826
}