{
    "descriptors" : [], 
    "FIPS" : "40123", 
    "full_name" : "Pontotoc County", 
    "common_name" : "", 
    "state" : "Oklahoma", 
    "county_seat" : "Ada", 
    "population" : 39002, 
    "population_desity" : 53.8, 
    "pop_change_rate" : 151.0, 
    "land_area" : 725.27, 
    "white_population" : 26687, 
    "black_population" : 902, 
    "native_indian_population" : 6512, 
    "asian_population" : 244, 
    "pacific_islander_population" : 17, 
    "hispanic_population" : 1523, 
    "other_race_ethnicity_population" : 425, 
    "multiple_race_population" : 2705, 
    "pop_male" : 18192, 
    "pop_female" : 19300, 
    "pop_0to4" : 2588, 
    "pop_5to9" : 2449, 
    "pop_10to14" : 2311, 
    "pop_15to19" : 2841, 
    "pop_20to24" : 3482, 
    "pop_25to34" : 4799, 
    "pop_35to44" : 4159, 
    "pop_45to54" : 4993, 
    "pop_55to64" : 4300, 
    "pop_65to74" : 3006, 
    "pop_75to84" : 1860, 
    "pop_85to120" : 704, 
    "median_age" : 35.7, 
    "median_age_male" : 34.0, 
    "median_age_female" : 37.3, 
    "number_households" : 14654, 
    "average_household_size" : 2.44, 
    "number_households_singleM_wo_child" : 1821, 
    "number_households_singleF_wo_child" : 2339, 
    "number_households_married_w_child" : 3000, 
    "number_households_married_wo_child" : 4207, 
    "number_households_singleM_w_child" : 425, 
    "number_households_singleF_w_child" : 1151, 
    "number_families" : 9698, 
    "average_family_size" : 2.99, 
    "housing_units" : 14654, 
    "housing_vacant" : 1941, 
    "owner_occupied_housing" : 9758, 
    "renter_occupied_housing" : 4896, 
    "number_farms" : 1313, 
    "average_farm_acreage" : 247, 
    "total_crop_acreage" : 69016
}