{
    "descriptors" : [], 
    "FIPS" : "46005", 
    "full_name" : "Beadle County", 
    "common_name" : "", 
    "state" : "South Dakota", 
    "county_seat" : "Huron", 
    "population" : 18386, 
    "population_desity" : 14.5, 
    "pop_change_rate" : 98.8, 
    "land_area" : 1264.81, 
    "white_population" : 15599, 
    "black_population" : 147, 
    "native_indian_population" : 189, 
    "asian_population" : 632, 
    "pacific_islander_population" : 17, 
    "hispanic_population" : 1337, 
    "other_race_ethnicity_population" : 529, 
    "multiple_race_population" : 285, 
    "pop_male" : 8755, 
    "pop_female" : 8643, 
    "pop_0to4" : 1300, 
    "pop_5to9" : 1091, 
    "pop_10to14" : 1076, 
    "pop_15to19" : 1147, 
    "pop_20to24" : 997, 
    "pop_25to34" : 2013, 
    "pop_35to44" : 1813, 
    "pop_45to54" : 2705, 
    "pop_55to64" : 2250, 
    "pop_65to74" : 1349, 
    "pop_75to84" : 1102, 
    "pop_85to120" : 555, 
    "median_age" : 41.2, 
    "median_age_male" : 39.6, 
    "median_age_female" : 42.7, 
    "number_households" : 7276, 
    "average_household_size" : 2.31, 
    "number_households_singleM_wo_child" : 1215, 
    "number_households_singleF_wo_child" : 1189, 
    "number_households_married_w_child" : 1362, 
    "number_households_married_wo_child" : 2238, 
    "number_households_singleM_w_child" : 208, 
    "number_households_singleF_w_child" : 462, 
    "number_families" : 4509, 
    "average_family_size" : 2.92, 
    "housing_units" : 7276, 
    "housing_vacant" : 1028, 
    "owner_occupied_housing" : 4813, 
    "renter_occupied_housing" : 2463, 
    "number_farms" : 754, 
    "average_farm_acreage" : 1053, 
    "total_crop_acreage" : 576930
}