{
    "descriptors" : [], 
    "FIPS" : "36123", 
    "full_name" : "Yates County", 
    "common_name" : "", 
    "state" : "New York", 
    "county_seat" : "Penn Yan", 
    "population" : 24964, 
    "population_desity" : 66.4, 
    "pop_change_rate" : -38.4, 
    "land_area" : 375.78, 
    "white_population" : 24647, 
    "black_population" : 203, 
    "native_indian_population" : 38, 
    "asian_population" : 97, 
    "pacific_islander_population" : 4, 
    "hispanic_population" : 421, 
    "other_race_ethnicity_population" : 90, 
    "multiple_race_population" : 269, 
    "pop_male" : 12278, 
    "pop_female" : 13070, 
    "pop_0to4" : 1581, 
    "pop_5to9" : 1602, 
    "pop_10to14" : 1835, 
    "pop_15to19" : 2156, 
    "pop_20to24" : 1712, 
    "pop_25to34" : 2363, 
    "pop_35to44" : 2590, 
    "pop_45to54" : 3797, 
    "pop_55to64" : 3496, 
    "pop_65to74" : 2281, 
    "pop_75to84" : 1370, 
    "pop_85to120" : 565, 
    "median_age" : 40.7, 
    "median_age_male" : 40.1, 
    "median_age_female" : 41.3, 
    "number_households" : 9517, 
    "average_household_size" : 2.53, 
    "number_households_singleM_wo_child" : 1159, 
    "number_households_singleF_wo_child" : 1403, 
    "number_households_married_w_child" : 1839, 
    "number_households_married_wo_child" : 3169, 
    "number_households_singleM_w_child" : 272, 
    "number_households_singleF_w_child" : 643, 
    "number_families" : 6404, 
    "average_family_size" : 3.06, 
    "housing_units" : 9517, 
    "housing_vacant" : 3974, 
    "owner_occupied_housing" : 7193, 
    "renter_occupied_housing" : 2324, 
    "number_farms" : 919, 
    "average_farm_acreage" : 138, 
    "total_crop_acreage" : 88113
}