{
    "descriptors" : [], 
    "FIPS" : "35028", 
    "full_name" : "Los Alamos County", 
    "common_name" : "", 
    "state" : "New Mexico", 
    "county_seat" : "Los Alamos", 
    "population" : 18638, 
    "population_desity" : 170.7, 
    "pop_change_rate" : 68.8, 
    "land_area" : 109.2, 
    "white_population" : 15765, 
    "black_population" : 102, 
    "native_indian_population" : 142, 
    "asian_population" : 1071, 
    "pacific_islander_population" : 10, 
    "hispanic_population" : 2646, 
    "other_race_ethnicity_population" : 393, 
    "multiple_race_population" : 467, 
    "pop_male" : 9029, 
    "pop_female" : 8921, 
    "pop_0to4" : 960, 
    "pop_5to9" : 1215, 
    "pop_10to14" : 1307, 
    "pop_15to19" : 1126, 
    "pop_20to24" : 498, 
    "pop_25to34" : 1713, 
    "pop_35to44" : 2327, 
    "pop_45to54" : 3347, 
    "pop_55to64" : 2771, 
    "pop_65to74" : 1440, 
    "pop_75to84" : 848, 
    "pop_85to120" : 398, 
    "median_age" : 44.3, 
    "median_age_male" : 43.8, 
    "median_age_female" : 44.8, 
    "number_households" : 7663, 
    "average_household_size" : 2.33, 
    "number_households_singleM_wo_child" : 1174, 
    "number_households_singleF_wo_child" : 1009, 
    "number_households_married_w_child" : 1840, 
    "number_households_married_wo_child" : 2611, 
    "number_households_singleM_w_child" : 194, 
    "number_households_singleF_w_child" : 350, 
    "number_families" : 5199, 
    "average_family_size" : 2.86, 
    "housing_units" : 7663, 
    "housing_vacant" : 691, 
    "owner_occupied_housing" : 5828, 
    "renter_occupied_housing" : 1835, 
    "number_farms" : 9, 
    "average_farm_acreage" : 2, 
    "total_crop_acreage" : 0
}