{
    "descriptors" : [], 
    "FIPS" : "08057", 
    "full_name" : "Jackson County", 
    "common_name" : "", 
    "state" : "Colorado", 
    "county_seat" : "Walden", 
    "population" : 1393, 
    "population_desity" : 0.9, 
    "pop_change_rate" : -0.1, 
    "land_area" : 1620.97, 
    "white_population" : 1290, 
    "black_population" : 0, 
    "native_indian_population" : 17, 
    "asian_population" : 1, 
    "pacific_islander_population" : 0, 
    "hispanic_population" : 150, 
    "other_race_ethnicity_population" : 70, 
    "multiple_race_population" : 16, 
    "pop_male" : 736, 
    "pop_female" : 658, 
    "pop_0to4" : 62, 
    "pop_5to9" : 76, 
    "pop_10to14" : 83, 
    "pop_15to19" : 69, 
    "pop_20to24" : 64, 
    "pop_25to34" : 136, 
    "pop_35to44" : 162, 
    "pop_45to54" : 264, 
    "pop_55to64" : 221, 
    "pop_65to74" : 153, 
    "pop_75to84" : 87, 
    "pop_85to120" : 17, 
    "median_age" : 46.9, 
    "median_age_male" : 46.9, 
    "median_age_female" : 46.8, 
    "number_households" : 649, 
    "average_household_size" : 2.14, 
    "number_households_singleM_wo_child" : 124, 
    "number_households_singleF_wo_child" : 92, 
    "number_households_married_w_child" : 102, 
    "number_households_married_wo_child" : 223, 
    "number_households_singleM_w_child" : 18, 
    "number_households_singleF_w_child" : 17, 
    "number_families" : 396, 
    "average_family_size" : 2.72, 
    "housing_units" : 649, 
    "housing_vacant" : 637, 
    "owner_occupied_housing" : 430, 
    "renter_occupied_housing" : 219, 
    "number_farms" : 105, 
    "average_farm_acreage" : 3261, 
    "total_crop_acreage" : 65538
}