{
    "descriptors" : [], 
    "FIPS" : "48237", 
    "full_name" : "Jack County", 
    "common_name" : "", 
    "state" : "Texas", 
    "county_seat" : "Jacksboro", 
    "population" : 9440, 
    "population_desity" : 10.3, 
    "pop_change_rate" : 39.6, 
    "land_area" : 920.12, 
    "white_population" : 7913, 
    "black_population" : 340, 
    "native_indian_population" : 62, 
    "asian_population" : 31, 
    "pacific_islander_population" : 3, 
    "hispanic_population" : 1283, 
    "other_race_ethnicity_population" : 600, 
    "multiple_race_population" : 95, 
    "pop_male" : 5030, 
    "pop_female" : 4014, 
    "pop_0to4" : 485, 
    "pop_5to9" : 521, 
    "pop_10to14" : 622, 
    "pop_15to19" : 599, 
    "pop_20to24" : 629, 
    "pop_25to34" : 1143, 
    "pop_35to44" : 1232, 
    "pop_45to54" : 1395, 
    "pop_55to64" : 1068, 
    "pop_65to74" : 784, 
    "pop_75to84" : 443, 
    "pop_85to120" : 123, 
    "median_age" : 39.3, 
    "median_age_male" : 37.4, 
    "median_age_female" : 41.9, 
    "number_households" : 3136, 
    "average_household_size" : 2.52, 
    "number_households_singleM_wo_child" : 396, 
    "number_households_singleF_wo_child" : 409, 
    "number_households_married_w_child" : 753, 
    "number_households_married_wo_child" : 1038, 
    "number_households_singleM_w_child" : 80, 
    "number_households_singleF_w_child" : 185, 
    "number_families" : 2213, 
    "average_family_size" : 3.02, 
    "housing_units" : 3136, 
    "housing_vacant" : 959, 
    "owner_occupied_housing" : 2398, 
    "renter_occupied_housing" : 738, 
    "number_farms" : 864, 
    "average_farm_acreage" : 611, 
    "total_crop_acreage" : 35814
}