{
    "descriptors" : [], 
    "FIPS" : "48337", 
    "full_name" : "Montague County", 
    "common_name" : "", 
    "state" : "Texas", 
    "county_seat" : "Montague", 
    "population" : 20881, 
    "population_desity" : 22.3, 
    "pop_change_rate" : 116.2, 
    "land_area" : 938.27, 
    "white_population" : 18384, 
    "black_population" : 53, 
    "native_indian_population" : 175, 
    "asian_population" : 62, 
    "pacific_islander_population" : 4, 
    "hispanic_population" : 1930, 
    "other_race_ethnicity_population" : 717, 
    "multiple_race_population" : 324, 
    "pop_male" : 9665, 
    "pop_female" : 10054, 
    "pop_0to4" : 1234, 
    "pop_5to9" : 1283, 
    "pop_10to14" : 1259, 
    "pop_15to19" : 1183, 
    "pop_20to24" : 989, 
    "pop_25to34" : 1976, 
    "pop_35to44" : 2331, 
    "pop_45to54" : 2847, 
    "pop_55to64" : 2737, 
    "pop_65to74" : 2170, 
    "pop_75to84" : 1241, 
    "pop_85to120" : 469, 
    "median_age" : 43.4, 
    "median_age_male" : 42.3, 
    "median_age_female" : 44.4, 
    "number_households" : 7989, 
    "average_household_size" : 2.43, 
    "number_households_singleM_wo_child" : 977, 
    "number_households_singleF_wo_child" : 1176, 
    "number_households_married_w_child" : 1647, 
    "number_households_married_wo_child" : 2763, 
    "number_households_singleM_w_child" : 244, 
    "number_households_singleF_w_child" : 460, 
    "number_families" : 5548, 
    "average_family_size" : 2.93, 
    "housing_units" : 7989, 
    "housing_vacant" : 2142, 
    "owner_occupied_housing" : 6246, 
    "renter_occupied_housing" : 1743, 
    "number_farms" : 1454, 
    "average_farm_acreage" : 336, 
    "total_crop_acreage" : 74027
}