{
    "descriptors" : [], 
    "FIPS" : "48359", 
    "full_name" : "Oldham County", 
    "common_name" : "", 
    "state" : "Texas", 
    "county_seat" : "Vega", 
    "population" : 2130, 
    "population_desity" : 1.4, 
    "pop_change_rate" : 7.8, 
    "land_area" : 1501.42, 
    "white_population" : 1850, 
    "black_population" : 62, 
    "native_indian_population" : 13, 
    "asian_population" : 17, 
    "pacific_islander_population" : 0, 
    "hispanic_population" : 243, 
    "other_race_ethnicity_population" : 80, 
    "multiple_race_population" : 30, 
    "pop_male" : 1035, 
    "pop_female" : 1017, 
    "pop_0to4" : 100, 
    "pop_5to9" : 159, 
    "pop_10to14" : 249, 
    "pop_15to19" : 250, 
    "pop_20to24" : 58, 
    "pop_25to34" : 221, 
    "pop_35to44" : 220, 
    "pop_45to54" : 288, 
    "pop_55to64" : 252, 
    "pop_65to74" : 149, 
    "pop_75to84" : 81, 
    "pop_85to120" : 25, 
    "median_age" : 34.6, 
    "median_age_male" : 30.6, 
    "median_age_female" : 38.4, 
    "number_households" : 691, 
    "average_household_size" : 2.56, 
    "number_households_singleM_wo_child" : 56, 
    "number_households_singleF_wo_child" : 93, 
    "number_households_married_w_child" : 175, 
    "number_households_married_wo_child" : 264, 
    "number_households_singleM_w_child" : 11, 
    "number_households_singleF_w_child" : 38, 
    "number_families" : 516, 
    "average_family_size" : 2.97, 
    "housing_units" : 691, 
    "housing_vacant" : 150, 
    "owner_occupied_housing" : 474, 
    "renter_occupied_housing" : 217, 
    "number_farms" : 159, 
    "average_farm_acreage" : 5223, 
    "total_crop_acreage" : 94823
}