{
    "descriptors" : [], 
    "FIPS" : "48411", 
    "full_name" : "San Saba County", 
    "common_name" : "", 
    "state" : "Texas", 
    "county_seat" : "San Saba", 
    "population" : 6347, 
    "population_desity" : 5.6, 
    "pop_change_rate" : 21.6, 
    "land_area" : 1138.52, 
    "white_population" : 5166, 
    "black_population" : 204, 
    "native_indian_population" : 48, 
    "asian_population" : 13, 
    "pacific_islander_population" : 0, 
    "hispanic_population" : 1715, 
    "other_race_ethnicity_population" : 605, 
    "multiple_race_population" : 95, 
    "pop_male" : 3366, 
    "pop_female" : 2765, 
    "pop_0to4" : 354, 
    "pop_5to9" : 318, 
    "pop_10to14" : 362, 
    "pop_15to19" : 396, 
    "pop_20to24" : 466, 
    "pop_25to34" : 830, 
    "pop_35to44" : 613, 
    "pop_45to54" : 749, 
    "pop_55to64" : 866, 
    "pop_65to74" : 609, 
    "pop_75to84" : 384, 
    "pop_85to120" : 184, 
    "median_age" : 40.7, 
    "median_age_male" : 34.7, 
    "median_age_female" : 46.8, 
    "number_households" : 2257, 
    "average_household_size" : 2.41, 
    "number_households_singleM_wo_child" : 293, 
    "number_households_singleF_wo_child" : 325, 
    "number_households_married_w_child" : 448, 
    "number_households_married_wo_child" : 779, 
    "number_households_singleM_w_child" : 66, 
    "number_households_singleF_w_child" : 132, 
    "number_families" : 1563, 
    "average_family_size" : 2.9, 
    "housing_units" : 2257, 
    "housing_vacant" : 920, 
    "owner_occupied_housing" : 1714, 
    "renter_occupied_housing" : 543, 
    "number_farms" : 744, 
    "average_farm_acreage" : 902, 
    "total_crop_acreage" : 53223
}