{
    "descriptors" : [], 
    "FIPS" : "48485", 
    "full_name" : "Wichita County", 
    "common_name" : "", 
    "state" : "Texas", 
    "county_seat" : "Wichita Falls", 
    "population" : 132992, 
    "population_desity" : 210.1, 
    "pop_change_rate" : 149.2, 
    "land_area" : 632.86, 
    "white_population" : 101331, 
    "black_population" : 13811, 
    "native_indian_population" : 1394, 
    "asian_population" : 2669, 
    "pacific_islander_population" : 101, 
    "hispanic_population" : 21859, 
    "other_race_ethnicity_population" : 8368, 
    "multiple_race_population" : 3826, 
    "pop_male" : 67438, 
    "pop_female" : 64062, 
    "pop_0to4" : 8955, 
    "pop_5to9" : 8418, 
    "pop_10to14" : 8245, 
    "pop_15to19" : 10520, 
    "pop_20to24" : 12823, 
    "pop_25to34" : 18429, 
    "pop_35to44" : 15113, 
    "pop_45to54" : 17929, 
    "pop_55to64" : 13891, 
    "pop_65to74" : 8802, 
    "pop_75to84" : 6095, 
    "pop_85to120" : 2280, 
    "median_age" : 34.0, 
    "median_age_male" : 32.3, 
    "median_age_female" : 36.2, 
    "number_households" : 49016, 
    "average_household_size" : 2.44, 
    "number_households_singleM_wo_child" : 6434, 
    "number_households_singleF_wo_child" : 7928, 
    "number_households_married_w_child" : 9827, 
    "number_households_married_wo_child" : 12744, 
    "number_households_singleM_w_child" : 1497, 
    "number_households_singleF_w_child" : 4647, 
    "number_families" : 31663, 
    "average_family_size" : 3.02, 
    "housing_units" : 49016, 
    "housing_vacant" : 6550, 
    "owner_occupied_housing" : 30219, 
    "renter_occupied_housing" : 18797, 
    "number_farms" : 639, 
    "average_farm_acreage" : 574, 
    "total_crop_acreage" : 117135
}